atomic_save.py
auto_attention.py
cloud_run.py
concepts.py
config.py
data.py
generate.py
generate_all_training_data.py
generate_coding_only.py
huawei_npu.py
infini_attention.py
master_scalar.py
mini_cot_optimizer.py
mini_the_agentic_cli.py
model.py
registry.py
tokenizer.py
train_v001.py
training_upgrade_pipeline.py
cot_optimized_qkv-0.1.0.dist-info/METADATA
cot_optimized_qkv-0.1.0.dist-info/WHEEL
cot_optimized_qkv-0.1.0.dist-info/entry_points.txt
cot_optimized_qkv-0.1.0.dist-info/top_level.txt
cot_optimized_qkv-0.1.0.dist-info/RECORD
