Metadata-Version: 2.4
Name: CoT_Optimized_QKV
Version: 0.1.0
Summary: Chain-of-Thought Optimized QKV Attention - Infini-Attention transformers with DeepSeek reasoner CoT optimization
Home-page: https://github.com/boshangclean/DeepSeeker-LLM
Author: Bo Shang
Author-email: Bo Shang <bo@shang.software>
License: MIT
Project-URL: Homepage, https://github.com/boshangclean/DeepSeeker-LLM
Project-URL: Documentation, https://github.com/boshangclean/DeepSeeker-LLM#readme
Project-URL: Repository, https://github.com/boshangclean/DeepSeeker-LLM.git
Project-URL: Issues, https://github.com/boshangclean/DeepSeeker-LLM/issues
Keywords: transformer,attention,infini-attention,linear-attention,long-context,language-model,pytorch,machine-learning,deep-learning,cloud-run,angular,chain-of-thought,cot-optimization,deepseek
Classifier: Development Status :: 4 - Beta
Classifier: Intended Audience :: Science/Research
Classifier: License :: OSI Approved :: MIT License
Classifier: Programming Language :: Python :: 3
Classifier: Programming Language :: Python :: 3.9
Classifier: Programming Language :: Python :: 3.10
Classifier: Programming Language :: Python :: 3.11
Classifier: Programming Language :: Python :: 3.12
Classifier: Topic :: Scientific/Engineering :: Artificial Intelligence
Classifier: Operating System :: OS Independent
Requires-Python: >=3.9
Requires-Dist: torch>=2.0.0
Requires-Dist: numpy>=1.24.0
Requires-Dist: pyyaml>=6.0
Requires-Dist: aiohttp>=3.8.0
Requires-Dist: tqdm>=4.64.0
Provides-Extra: full
Requires-Dist: openai>=1.0.0; extra == "full"
Requires-Dist: transformers>=4.36.0; extra == "full"
Requires-Dist: datasets>=2.14.0; extra == "full"
Requires-Dist: accelerate>=0.25.0; extra == "full"
Requires-Dist: wandb>=0.16.0; extra == "full"
Requires-Dist: huggingface_hub>=0.19.0; extra == "full"
Provides-Extra: bench
Requires-Dist: lm-eval>=0.4.2; extra == "bench"
Provides-Extra: dev
Requires-Dist: pytest>=7.0.0; extra == "dev"
Requires-Dist: pytest-cov>=4.0.0; extra == "dev"
Requires-Dist: black>=23.0.0; extra == "dev"
Requires-Dist: ruff>=0.1.0; extra == "dev"
Requires-Dist: build>=1.0.0; extra == "dev"
Requires-Dist: twine>=4.0.0; extra == "dev"
Provides-Extra: cloud
Requires-Dist: google-cloud-run>=0.10.0; extra == "cloud"
Requires-Dist: google-auth>=2.0.0; extra == "cloud"
Provides-Extra: huawei
Requires-Dist: torch_npu; extra == "huawei"
Dynamic: author
Dynamic: home-page
Dynamic: requires-python
